{

    "return_function_params": {
        "mu": 0,
        "sigma": 0.28,
        "current_price": 100,
        "N": 1000,
        "T": 365
    },
    "return_function": "log_normal_return",
    "save_logs": false,
    "strategy_function_params" : {
        "amount_multiple":   1.0,
        
        "percent_allocated": 0.5,
        
        "rebalance_threshold_down":  0.8,
        "rebalance_threshold_up":  1.2,

        "max_rebalances": 365,
        "rebalance_every": 365,

        "cash_interest": 0.00,
        "coin_interest": 0.00,

        
        "option_every_itervals":  3000 ,
        "option_duration":  22,
        "option_amount_pct_of_notional":  0.3,
        "option_straddle_pct_from_strike":   0.07,
        
        "ticker_name" :  "ETH",
        "benchmark_strategy_name": "Buy and Hold"

        
        
                                }
    ,"plot_params": {"show_plot": false
                    ,"ci":0.975
                    }

}